fluentstream/__init__.py
fluentstream/stream.py
fluentstream-0.1.0.dist-info/WHEEL
fluentstream-0.1.0.dist-info/METADATA
fluentstream-0.1.0.dist-info/RECORD
