Metadata-Version: 2.1
Name: fluentstream
Version: 0.1.0
Summary: A stream abstraction with a fluent interface. Inspired by Java 8 streams.
Home-page: https://github.com/binarybusiness/fluentstream.git
Author: Mikael M
Author-email: binarybusiness@gmail.com
Requires-Python: >=3.8,<4.0
Classifier: Programming Language :: Python :: 3
Classifier: Programming Language :: Python :: 3.10
Classifier: Programming Language :: Python :: 3.8
Classifier: Programming Language :: Python :: 3.9
Project-URL: Repository, https://github.com/binarybusiness/fluentstream.git
